[
  {
    "name": "Mary",
    "meaning": "Hebrew origin, meaning 'beloved' or 'sea of bitterness'"
  },
  {
    "name": "Patricia",
    "meaning": "Latin origin, meaning 'noblewoman'"
  },
  {
    "name": "Jennifer",
    "meaning": "Welsh origin, meaning 'fair one' or 'white wave'"
  },
  {
    "name": "Linda",
    "meaning": "Spanish origin, meaning 'pretty'"
  },
  {
    "name": "Barbara",
    "meaning": "Greek origin, meaning 'foreign woman'"
  },
  {
    "name": "Elizabeth",
    "meaning": "Hebrew origin, meaning 'my God is an oath'"
  },
  {
    "name": "Susan",
    "meaning": "Hebrew origin, meaning 'lily'"
  },
  {
    "name": "Jessica",
    "meaning": "Hebrew origin, possibly meaning 'God beholds'"
  },
  {
    "name": "Sarah",
    "meaning": "Hebrew origin, meaning 'princess'"
  },
  {
    "name": "Karen",
    "meaning": "Scandinavian form of Katherine, meaning 'pure'"
  },
  {
    "name": "Lisa",
    "meaning": "Hebrew origin, short for Elizabeth"
  },
  {
    "name": "Nancy",
    "meaning": "Hebrew origin, form of Anne, meaning 'grace'"
  },
  {
    "name": "Betty",
    "meaning": "Hebrew origin, short for Elizabeth, meaning 'oath of God'"
  },
  {
    "name": "Margaret",
    "meaning": "Greek origin, meaning 'pearl'"
  },
  {
    "name": "Sandra",
    "meaning": "Greek origin, short for Alexandra, meaning 'defender of men'"
  },
  {
    "name": "Ashley",
    "meaning": "Old English origin, meaning 'ash tree meadow'"
  },
  {
    "name": "Dorothy",
    "meaning": "Greek origin, meaning 'gift of God'"
  },
  {
    "name": "Kimberly",
    "meaning": "Old English origin, meaning 'Cyneburg's meadow'"
  },
  {
    "name": "Emily",
    "meaning": "Latin origin, meaning 'rival' or 'industrious'"
  },
  {
    "name": "Donna",
    "meaning": "Italian origin, meaning 'woman' or 'lady'"
  },
  {
    "name": "Carol",
    "meaning": "Old French and German origin, meaning 'free woman'"
  },
  {
    "name": "Ruth",
    "meaning": "Hebrew origin, meaning 'companion' or 'friend'"
  },
  {
    "name": "Sharon",
    "meaning": "Hebrew origin, meaning 'a fertile plain'"
  },
  {
    "name": "Michelle",
    "meaning": "French form of Michael, meaning 'who is like God?'"
  },
  {
    "name": "Laura",
    "meaning": "Latin origin, meaning 'laurel tree'"
  },
  {
    "name": "Sarah",
    "meaning": "Hebrew origin, meaning 'princess'"
  },
  {
    "name": "Kathy",
    "meaning": "Greek origin, short for Katherine, meaning 'pure'"
  },
  {
    "name": "Amy",
    "meaning": "Old French origin, meaning 'beloved'"
  },
  {
    "name": "Angela",
    "meaning": "Greek origin, meaning 'messenger of God'"
  },
  {
    "name": "Melissa",
    "meaning": "Greek origin, meaning 'honey bee'"
  },
  {
    "name": "Brenda",
    "meaning": "Norse origin, meaning 'sword' or 'torch'"
  },
  {
    "name": "Emma",
    "meaning": "Old Germanic origin, meaning 'whole' or 'universal'"
  },
  {
    "name": "Megan",
    "meaning": "Welsh origin, meaning 'strong' or 'capable'"
  },
  {
    "name": "Stephanie",
    "meaning": "Greek origin, meaning 'crown'"
  },
  {
    "name": "Rebecca",
    "meaning": "Hebrew origin, meaning 'to bind' or 'captivating'"
  },
  {
    "name": "Sharon",
    "meaning": "Hebrew origin, meaning 'fertile plain'"
  },
  {
    "name": "Laura",
    "meaning": "Latin origin, meaning 'bay laurel'"
  },
  {
    "name": "Cynthia",
    "meaning": "Greek origin, meaning 'moon goddess'"
  },
  {
    "name": "Kathleen",
    "meaning": "Irish form of Katherine, meaning 'pure'"
  },
  {
    "name": "Amy",
    "meaning": "Old French origin, meaning 'beloved'"
  },
  {
    "name": "Shirley",
    "meaning": "Old English origin, meaning 'bright clearing'"
  },
  {
    "name": "Anna",
    "meaning": "Hebrew origin, meaning 'grace'"
  },
  {
    "name": "Virginia",
    "meaning": "Latin origin, meaning 'pure' or 'virginal'"
  },
  {
    "name": "Maria",
    "meaning": "Latin form of Mary, meaning 'beloved'"
  },
  {
    "name": "Janice",
    "meaning": "Hebrew origin, form of Jane, meaning 'God is gracious'"
  },
  {
    "name": "Kelly",
    "meaning": "Irish origin, meaning 'warrior' or 'church'"
  },
  {
    "name": "Nicole",
    "meaning": "French form of Nicholas, meaning 'victory of the people'"
  },
  {
    "name": "Judy",
    "meaning": "Hebrew origin, form of Judith, meaning 'woman of Judea'"
  },
  {
    "name": "Christina",
    "meaning": "Latin origin, meaning 'follower of Christ'"
  },
  {
    "name": "Katharine",
    "meaning": "Greek origin, meaning 'pure'"
  },
  {
    "name": "Joan",
    "meaning": "Hebrew origin, form of John, meaning 'God is gracious'"
  },
  {
    "name": "Evelyn",
    "meaning": "Old English and Norman origin, meaning 'wished for child'"
  },
  {
    "name": "Julie",
    "meaning": "Latin origin, meaning 'youthful'"
  },
  {
    "name": "Heather",
    "meaning": "Old English nature name for the heather plant"
  },
  {
    "name": "Teresa",
    "meaning": "Greek origin, meaning 'to harvest' or 'summer'"
  },
  {
    "name": "Gloria",
    "meaning": "Latin origin, meaning 'glory'"
  },
  {
    "name": "Carolyn",
    "meaning": "Old French and German origin, form of Carol"
  },
  {
    "name": "Ann",
    "meaning": "Hebrew origin, meaning 'grace'"
  },
  {
    "name": "Joyce",
    "meaning": "Old French origin, meaning 'lord'"
  },
  {
    "name": "Diana",
    "meaning": "Latin origin, name of the Roman goddess of the hunt"
  },
  {
    "name": "Debra",
    "meaning": "Hebrew origin, meaning 'bee'"
  },
  {
    "name": "Rachel",
    "meaning": "Hebrew origin, meaning 'ewe' or 'lamb'"
  },
  {
    "name": "Cheryl",
    "meaning": "French origin, meaning 'darling' or 'beloved'"
  },
  {
    "name": "Janet",
    "meaning": "Hebrew origin, form of Jane, meaning 'God is gracious'"
  },
  {
    "name": "Catherine",
    "meaning": "Greek origin, meaning 'pure'"
  },
  {
    "name": "Frances",
    "meaning": "Latin origin, meaning 'French woman'"
  },
  {
    "name": "Ann",
    "meaning": "Hebrew origin, meaning 'grace' or 'favor'"
  },
  {
    "name": "Joyce",
    "meaning": "Old French origin, meaning 'rejoice'"
  },
  {
    "name": "Olivia",
    "meaning": "Latin origin, meaning 'olive tree'"
  },
  {
    "name": "Ava",
    "meaning": "Latin or Hebrew origin, meaning 'life' or 'birdlike'"
  },
  {
    "name": "Isabella",
    "meaning": "Hebrew origin via Italian, meaning 'devoted to God'"
  },
  {
    "name": "Sophia",
    "meaning": "Greek origin, meaning 'wisdom'"
  },
  {
    "name": "Mia",
    "meaning": "Scandinavian origin, meaning 'mine' or 'beloved'"
  },
  {
    "name": "Charlotte",
    "meaning": "French form of Charles, meaning 'free woman'"
  },
  {
    "name": "Amelia",
    "meaning": "Old Germanic origin, meaning 'work' or 'industrious'"
  },
  {
    "name": "Harper",
    "meaning": "Old English occupational name meaning 'harp player'"
  },
  {
    "name": "Evelyn",
    "meaning": "Old English origin, meaning 'wished for child'"
  },
  {
    "name": "Abigail",
    "meaning": "Hebrew origin, meaning 'my father rejoices'"
  },
  {
    "name": "Ella",
    "meaning": "Old Germanic origin, meaning 'all' or 'completely'"
  },
  {
    "name": "Scarlett",
    "meaning": "Old French origin, meaning 'red'"
  },
  {
    "name": "Grace",
    "meaning": "Latin origin, meaning 'God's grace' or 'charm'"
  },
  {
    "name": "Chloe",
    "meaning": "Greek origin, meaning 'green shoot' or 'blooming'"
  },
  {
    "name": "Victoria",
    "meaning": "Latin origin, meaning 'victory'"
  },
  {
    "name": "Aria",
    "meaning": "Italian origin, meaning 'air' or 'song'"
  },
  {
    "name": "Lillian",
    "meaning": "Latin origin, meaning 'lily'"
  },
  {
    "name": "Lily",
    "meaning": "Old English and Latin origin, meaning 'lily flower'"
  },
  {
    "name": "Zoey",
    "meaning": "Greek origin, meaning 'life'"
  },
  {
    "name": "Penelope",
    "meaning": "Greek origin, meaning 'weaver'"
  },
  {
    "name": "Layla",
    "meaning": "Arabic origin, meaning 'night' or 'dark beauty'"
  },
  {
    "name": "Riley",
    "meaning": "Irish origin, meaning 'courageous' or 'valiant'"
  },
  {
    "name": "Zo\u00e9",
    "meaning": "Greek origin, meaning 'life'"
  },
  {
    "name": "Nora",
    "meaning": "Irish origin, short for Honora, meaning 'honor'"
  },
  {
    "name": "Lily",
    "meaning": "Old English and Latin origin, meaning 'lily flower'"
  },
  {
    "name": "Eleanor",
    "meaning": "Old French and Greek origin, meaning 'bright one'"
  },
  {
    "name": "Hannah",
    "meaning": "Hebrew origin, meaning 'grace' or 'favor'"
  },
  {
    "name": "Lillian",
    "meaning": "Latin origin, from the lily flower"
  },
  {
    "name": "Addison",
    "meaning": "Old English origin, meaning 'son of Adam'"
  },
  {
    "name": "Aubrey",
    "meaning": "Old Germanic origin, meaning 'elf ruler'"
  },
  {
    "name": "Ellie",
    "meaning": "Greek origin, short form of Eleanor, meaning 'bright'"
  },
  {
    "name": "Stella",
    "meaning": "Latin origin, meaning 'star'"
  },
  {
    "name": "Natalie",
    "meaning": "Latin origin, meaning 'born on Christmas Day'"
  },
  {
    "name": "Zoe",
    "meaning": "Greek origin, meaning 'life'"
  },
  {
    "name": "Leah",
    "meaning": "Hebrew origin, meaning 'weary' or 'cow'"
  },
  {
    "name": "Hazel",
    "meaning": "Old English nature name for the hazel tree"
  },
  {
    "name": "Violet",
    "meaning": "Latin origin, from the violet flower"
  },
  {
    "name": "Aurora",
    "meaning": "Latin origin, meaning 'dawn'"
  },
  {
    "name": "Savannah",
    "meaning": "Spanish origin, meaning 'treeless plain'"
  },
  {
    "name": "Audrey",
    "meaning": "Old English origin, meaning 'noble strength'"
  },
  {
    "name": "Brooklyn",
    "meaning": "Dutch origin, from the New York borough"
  },
  {
    "name": "Bella",
    "meaning": "Italian origin, meaning 'beautiful'"
  },
  {
    "name": "Claire",
    "meaning": "French and Latin origin, meaning 'clear' or 'bright'"
  },
  {
    "name": "Skylar",
    "meaning": "Dutch origin, meaning 'scholar'"
  },
  {
    "name": "Lucy",
    "meaning": "Latin origin, meaning 'light'"
  },
  {
    "name": "Paisley",
    "meaning": "Scottish origin, from a town in Scotland"
  },
  {
    "name": "Everly",
    "meaning": "Old English origin, meaning 'boar meadow'"
  },
  {
    "name": "Anna",
    "meaning": "Hebrew origin, meaning 'grace'"
  },
  {
    "name": "Caroline",
    "meaning": "Old French and German form of Charles, meaning 'free woman'"
  },
  {
    "name": "Genesis",
    "meaning": "Greek origin, meaning 'origin' or 'beginning'"
  },
  {
    "name": "Aaliyah",
    "meaning": "Arabic origin, meaning 'high-born' or 'exalted'"
  },
  {
    "name": "Kennedy",
    "meaning": "Irish origin, meaning 'helmeted chief'"
  },
  {
    "name": "Kinsley",
    "meaning": "Old English origin, meaning 'king's meadow'"
  },
  {
    "name": "Allison",
    "meaning": "Old Germanic origin, meaning 'noble'"
  },
  {
    "name": "Maya",
    "meaning": "Hebrew and Sanskrit origin, meaning 'water' or 'illusion'"
  },
  {
    "name": "Sophie",
    "meaning": "Greek origin, meaning 'wisdom'"
  },
  {
    "name": "Sadie",
    "meaning": "Hebrew origin, form of Sarah, meaning 'princess'"
  },
  {
    "name": "Madeline",
    "meaning": "French form of Magdalene, meaning 'of Magdala'"
  },
  {
    "name": "Peyton",
    "meaning": "Old English origin, meaning 'fighting man's estate'"
  },
  {
    "name": "Rylee",
    "meaning": "Irish origin, variant of Riley, meaning 'courageous'"
  },
  {
    "name": "Piper",
    "meaning": "Old English occupational name meaning 'flute player'"
  },
  {
    "name": "Taylor",
    "meaning": "Old French occupational name meaning 'tailor'"
  },
  {
    "name": "Alexis",
    "meaning": "Greek origin, meaning 'defender'"
  },
  {
    "name": "Katherine",
    "meaning": "Greek origin, meaning 'pure'"
  },
  {
    "name": "Kayla",
    "meaning": "Hebrew origin, meaning 'crown of laurels'"
  },
  {
    "name": "Sydney",
    "meaning": "Old English origin, meaning 'wide island'"
  },
  {
    "name": "Mackenzie",
    "meaning": "Scottish Gaelic origin, meaning 'son of Kenneth'"
  },
  {
    "name": "Madison",
    "meaning": "Old English origin, meaning 'son of Maud'"
  },
  {
    "name": "Naomi",
    "meaning": "Hebrew origin, meaning 'pleasantness'"
  },
  {
    "name": "Eliana",
    "meaning": "Hebrew origin, meaning 'my God has answered'"
  },
  {
    "name": "Valentina",
    "meaning": "Latin origin, meaning 'strong' or 'healthy'"
  },
  {
    "name": "Willow",
    "meaning": "Old English nature name for the willow tree"
  },
  {
    "name": "Brianna",
    "meaning": "Irish origin, feminine form of Brian, meaning 'strong'"
  },
  {
    "name": "Kaylee",
    "meaning": "Hebrew origin, variant of Kayla, meaning 'crown'"
  },
  {
    "name": "Autumn",
    "meaning": "Latin origin, referring to the season of autumn"
  },
  {
    "name": "Lyla",
    "meaning": "Arabic origin, variant of Layla, meaning 'night'"
  },
  {
    "name": "Nevaeh",
    "meaning": "American invented name, 'heaven' spelled backward"
  },
  {
    "name": "Ariana",
    "meaning": "Greek and Welsh origin, meaning 'silver'"
  },
  {
    "name": "Jade",
    "meaning": "Spanish origin, from the precious green stone"
  },
  {
    "name": "Josephine",
    "meaning": "French form of Joseph, meaning 'God will add'"
  },
  {
    "name": "Alice",
    "meaning": "Old Germanic origin, meaning 'noble'"
  },
  {
    "name": "Samantha",
    "meaning": "Hebrew and Aramaic origin, meaning 'listener'"
  },
  {
    "name": "Luna",
    "meaning": "Latin origin, meaning 'moon'"
  },
  {
    "name": "Jasmine",
    "meaning": "Persian origin, from the jasmine flower"
  },
  {
    "name": "Autumn",
    "meaning": "Latin origin, referring to the fall season"
  },
  {
    "name": "Quinn",
    "meaning": "Irish origin, meaning 'counsel' or 'reason'"
  },
  {
    "name": "Eva",
    "meaning": "Hebrew origin, form of Eve, meaning 'life'"
  },
  {
    "name": "Phoebe",
    "meaning": "Greek origin, meaning 'bright' or 'pure'"
  },
  {
    "name": "Serenity",
    "meaning": "English origin, meaning 'peaceful' or 'calm'"
  },
  {
    "name": "Isla",
    "meaning": "Scottish origin, from the River Isla, meaning 'island'"
  },
  {
    "name": "Eliza",
    "meaning": "Hebrew origin, short for Elizabeth, meaning 'God's promise'"
  },
  {
    "name": "Molly",
    "meaning": "Hebrew origin, form of Mary, meaning 'beloved'"
  },
  {
    "name": "Mackenzie",
    "meaning": "Scottish Gaelic origin, meaning 'child of Kenneth'"
  },
  {
    "name": "Ariel",
    "meaning": "Hebrew origin, meaning 'lion of God'"
  },
  {
    "name": "Emelia",
    "meaning": "Latin origin, variant of Amelia, meaning 'industrious'"
  },
  {
    "name": "Elena",
    "meaning": "Greek origin, meaning 'bright' or 'shining'"
  },
  {
    "name": "Lydia",
    "meaning": "Greek origin, meaning 'from Lydia'"
  },
  {
    "name": "Julia",
    "meaning": "Latin origin, meaning 'youthful'"
  },
  {
    "name": "Destiny",
    "meaning": "Old French origin, meaning 'fate' or 'destiny'"
  },
  {
    "name": "Fiona",
    "meaning": "Irish and Scottish origin, meaning 'fair' or 'white'"
  },
  {
    "name": "Deborah",
    "meaning": "Hebrew origin, meaning 'bee'"
  },
  {
    "name": "Esther",
    "meaning": "Persian or Hebrew origin, meaning 'star'"
  },
  {
    "name": "Miriam",
    "meaning": "Hebrew origin, possibly meaning 'beloved'"
  },
  {
    "name": "Naomi",
    "meaning": "Hebrew origin, meaning 'pleasantness'"
  },
  {
    "name": "Abigail",
    "meaning": "Hebrew origin, meaning 'my father rejoices'"
  },
  {
    "name": "Dinah",
    "meaning": "Hebrew origin, meaning 'judged' or 'vindicated'"
  },
  {
    "name": "Judith",
    "meaning": "Hebrew origin, meaning 'woman of Judea'"
  },
  {
    "name": "Leah",
    "meaning": "Hebrew origin, meaning 'weary'"
  },
  {
    "name": "Priscilla",
    "meaning": "Latin origin, meaning 'ancient'"
  },
  {
    "name": "Rachel",
    "meaning": "Hebrew origin, meaning 'ewe'"
  },
  {
    "name": "Rebekah",
    "meaning": "Hebrew origin, meaning 'to bind' or 'snare'"
  },
  {
    "name": "Salome",
    "meaning": "Hebrew origin, meaning 'peace'"
  },
  {
    "name": "Zilpah",
    "meaning": "Hebrew origin, meaning 'frailty'"
  },
  {
    "name": "Hagar",
    "meaning": "Hebrew origin, meaning 'flight' or 'stranger'"
  },
  {
    "name": "Joanna",
    "meaning": "Hebrew origin, meaning 'God is gracious'"
  },
  {
    "name": "Martha",
    "meaning": "Aramaic origin, meaning 'mistress' or 'lady'"
  },
  {
    "name": "Mary Magdalene",
    "meaning": "Hebrew origin, meaning 'beloved' and 'from Magdala'"
  },
  {
    "name": "Rhoda",
    "meaning": "Greek origin, meaning 'rose'"
  },
  {
    "name": "Susanna",
    "meaning": "Hebrew origin, meaning 'lily'"
  },
  {
    "name": "Tamar",
    "meaning": "Hebrew origin, meaning 'date palm'"
  },
  {
    "name": "Bathsheba",
    "meaning": "Hebrew origin, meaning 'daughter of the oath'"
  },
  {
    "name": "Kezia",
    "meaning": "Hebrew origin, meaning 'cassia' or 'cinnamon'"
  },
  {
    "name": "Jemima",
    "meaning": "Hebrew origin, meaning 'dove'"
  },
  {
    "name": "Delilah",
    "meaning": "Hebrew origin, meaning 'delicate' or 'languishing'"
  },
  {
    "name": "Rahel",
    "meaning": "Hebrew origin, variant of Rachel"
  },
  {
    "name": "Sapphira",
    "meaning": "Hebrew origin, meaning 'sapphire'"
  },
  {
    "name": "Zipporah",
    "meaning": "Hebrew origin, meaning 'bird'"
  },
  {
    "name": "Tirzah",
    "meaning": "Hebrew origin, meaning 'pleasant'"
  },
  {
    "name": "Abigail",
    "meaning": "Hebrew origin, meaning 'my father is joy'"
  },
  {
    "name": "Phoebe",
    "meaning": "Greek origin, meaning 'radiant'"
  },
  {
    "name": "Rose",
    "meaning": "Latin origin, from the rose flower"
  },
  {
    "name": "Iris",
    "meaning": "Greek origin, meaning 'rainbow'"
  },
  {
    "name": "Ivy",
    "meaning": "Old English nature name for the climbing plant"
  },
  {
    "name": "Jade",
    "meaning": "Spanish origin, from the precious green stone"
  },
  {
    "name": "Juniper",
    "meaning": "Latin origin, from the juniper tree"
  },
  {
    "name": "Magnolia",
    "meaning": "French origin, from the magnolia tree"
  },
  {
    "name": "Meadow",
    "meaning": "Old English nature name meaning 'meadow'"
  },
  {
    "name": "Pearl",
    "meaning": "Latin origin, meaning 'pearl'"
  },
  {
    "name": "Poppy",
    "meaning": "Old English nature name for the poppy flower"
  },
  {
    "name": "Sage",
    "meaning": "Latin origin, from the herb, meaning 'wise'"
  },
  {
    "name": "Skye",
    "meaning": "Scottish origin, from the Isle of Skye"
  },
  {
    "name": "Summer",
    "meaning": "Old English origin, referring to the warm season"
  },
  {
    "name": "Willow",
    "meaning": "Old English origin, referring to the willow tree"
  },
  {
    "name": "Wren",
    "meaning": "Old English origin, from the small songbird"
  },
  {
    "name": "Zinnia",
    "meaning": "Latin origin, from the zinnia flower"
  },
  {
    "name": "Bay",
    "meaning": "English nature name meaning 'inlet of water'"
  },
  {
    "name": "Blossom",
    "meaning": "Old English origin, meaning 'flower'"
  },
  {
    "name": "Brook",
    "meaning": "Old English origin, meaning 'small stream'"
  },
  {
    "name": "Clover",
    "meaning": "Old English nature name for the clover plant"
  },
  {
    "name": "Coral",
    "meaning": "Latin origin, from the marine organism"
  },
  {
    "name": "Crystal",
    "meaning": "Greek origin, meaning 'ice' or 'clear'"
  },
  {
    "name": "Dahlia",
    "meaning": "Swedish origin, from the dahlia flower"
  },
  {
    "name": "Dawn",
    "meaning": "Old English origin, meaning 'the first light of day'"
  },
  {
    "name": "Dusk",
    "meaning": "Old English origin, meaning 'twilight'"
  },
  {
    "name": "Fern",
    "meaning": "Old English nature name for the fern plant"
  },
  {
    "name": "Flora",
    "meaning": "Latin origin, meaning 'flower'"
  },
  {
    "name": "Fleur",
    "meaning": "French origin, meaning 'flower'"
  },
  {
    "name": "Haven",
    "meaning": "Old English origin, meaning 'safe place'"
  },
  {
    "name": "Holly",
    "meaning": "Old English nature name for the holly plant"
  },
  {
    "name": "Jade",
    "meaning": "Spanish origin, meaning 'stone of the side'"
  },
  {
    "name": "Lake",
    "meaning": "English nature name referring to a body of water"
  },
  {
    "name": "Laurel",
    "meaning": "Latin origin, from the laurel tree"
  },
  {
    "name": "Lark",
    "meaning": "Old English nature name for the songbird"
  },
  {
    "name": "Leaf",
    "meaning": "Old English nature name"
  },
  {
    "name": "Lotus",
    "meaning": "Greek origin, from the lotus flower"
  },
  {
    "name": "Luna",
    "meaning": "Latin origin, meaning 'moon'"
  },
  {
    "name": "Maple",
    "meaning": "Old English nature name for the maple tree"
  },
  {
    "name": "Marina",
    "meaning": "Latin origin, meaning 'of the sea'"
  },
  {
    "name": "Marigold",
    "meaning": "Old English origin, from the marigold flower"
  },
  {
    "name": "Mist",
    "meaning": "Old English nature name"
  },
  {
    "name": "Ocean",
    "meaning": "Greek origin, meaning 'large body of water'"
  },
  {
    "name": "Olive",
    "meaning": "Latin origin, from the olive tree"
  },
  {
    "name": "Orchid",
    "meaning": "Greek origin, from the orchid flower"
  },
  {
    "name": "Petal",
    "meaning": "Greek origin, from the petal of a flower"
  },
  {
    "name": "Rain",
    "meaning": "Old English nature name for rainfall"
  },
  {
    "name": "Rainbow",
    "meaning": "Old English compound meaning 'arc of colors'"
  },
  {
    "name": "River",
    "meaning": "Latin origin, meaning 'flowing water'"
  },
  {
    "name": "Robin",
    "meaning": "Old Germanic origin, from the robin bird"
  },
  {
    "name": "Saffron",
    "meaning": "Arabic origin, from the spice and yellow color"
  },
  {
    "name": "Sandy",
    "meaning": "Old English origin, meaning 'sandy place'"
  },
  {
    "name": "Sierra",
    "meaning": "Spanish origin, meaning 'mountain range'"
  },
  {
    "name": "Soleil",
    "meaning": "French origin, meaning 'sun'"
  },
  {
    "name": "Sparrow",
    "meaning": "Old English nature name for the sparrow bird"
  },
  {
    "name": "Spring",
    "meaning": "Old English origin, referring to the season"
  },
  {
    "name": "Star",
    "meaning": "Old English origin, meaning 'celestial star'"
  },
  {
    "name": "Storm",
    "meaning": "Old Norse origin, meaning 'tempest'"
  },
  {
    "name": "Sunflower",
    "meaning": "Old English compound nature name"
  },
  {
    "name": "Sunny",
    "meaning": "English origin, meaning 'bright' or 'cheerful'"
  },
  {
    "name": "Terra",
    "meaning": "Latin origin, meaning 'earth'"
  },
  {
    "name": "Wisteria",
    "meaning": "Modern English, from the wisteria vine flower"
  },
  {
    "name": "Yarrow",
    "meaning": "Old English nature name for the flowering plant"
  },
  {
    "name": "Athena",
    "meaning": "Greek origin, name of the goddess of wisdom"
  },
  {
    "name": "Aphrodite",
    "meaning": "Greek origin, name of the goddess of love"
  },
  {
    "name": "Artemis",
    "meaning": "Greek origin, name of the goddess of the hunt"
  },
  {
    "name": "Cassandra",
    "meaning": "Greek origin, meaning 'she who entangles men'"
  },
  {
    "name": "Circe",
    "meaning": "Greek origin, meaning 'bird'"
  },
  {
    "name": "Daphne",
    "meaning": "Greek origin, meaning 'laurel tree'"
  },
  {
    "name": "Demeter",
    "meaning": "Greek origin, name of goddess of harvest"
  },
  {
    "name": "Elektra",
    "meaning": "Greek origin, meaning 'amber' or 'bright'"
  },
  {
    "name": "Europa",
    "meaning": "Greek mythological name, meaning 'wide-gazing'"
  },
  {
    "name": "Freya",
    "meaning": "Old Norse origin, name of the goddess of love"
  },
  {
    "name": "Gaia",
    "meaning": "Greek origin, name of the earth goddess"
  },
  {
    "name": "Harmonia",
    "meaning": "Greek origin, meaning 'harmony'"
  },
  {
    "name": "Hebe",
    "meaning": "Greek origin, meaning 'youth'"
  },
  {
    "name": "Hecate",
    "meaning": "Greek origin, meaning 'far-reaching'"
  },
  {
    "name": "Helen",
    "meaning": "Greek origin, meaning 'bright' or 'shining'"
  },
  {
    "name": "Hera",
    "meaning": "Greek origin, name of the queen of the gods"
  },
  {
    "name": "Hero",
    "meaning": "Greek origin, meaning 'hero' or 'warrior'"
  },
  {
    "name": "Hypatia",
    "meaning": "Greek origin, meaning 'highest'"
  },
  {
    "name": "Io",
    "meaning": "Greek mythological name, loved by Zeus"
  },
  {
    "name": "Iris",
    "meaning": "Greek origin, meaning 'rainbow', messenger goddess"
  },
  {
    "name": "Isis",
    "meaning": "Egyptian origin, name of the goddess of magic"
  },
  {
    "name": "Isolde",
    "meaning": "Welsh and Old German origin, meaning 'ice ruler'"
  },
  {
    "name": "Juno",
    "meaning": "Latin origin, name of the Roman queen of the gods"
  },
  {
    "name": "Maeve",
    "meaning": "Irish origin, meaning 'intoxicating'"
  },
  {
    "name": "Medea",
    "meaning": "Greek origin, meaning 'cunning' or 'planner'"
  },
  {
    "name": "Minerva",
    "meaning": "Latin origin, Roman goddess of wisdom"
  },
  {
    "name": "Nike",
    "meaning": "Greek origin, name of the goddess of victory"
  },
  {
    "name": "Nyx",
    "meaning": "Greek origin, name of the goddess of night"
  },
  {
    "name": "Pandora",
    "meaning": "Greek origin, meaning 'all gifted'"
  },
  {
    "name": "Penelope",
    "meaning": "Greek origin, meaning 'weaver'"
  },
  {
    "name": "Persephone",
    "meaning": "Greek origin, meaning 'bringer of destruction'"
  },
  {
    "name": "Psyche",
    "meaning": "Greek origin, meaning 'soul' or 'butterfly'"
  },
  {
    "name": "Selene",
    "meaning": "Greek origin, name of the moon goddess"
  },
  {
    "name": "Thalia",
    "meaning": "Greek origin, meaning 'to bloom' or 'joyful'"
  },
  {
    "name": "Venus",
    "meaning": "Latin origin, name of the Roman goddess of love"
  },
  {
    "name": "Vesta",
    "meaning": "Latin origin, name of the Roman goddess of the hearth"
  },
  {
    "name": "Aoife",
    "meaning": "Irish origin, meaning 'beautiful' or 'radiant'"
  },
  {
    "name": "Brigid",
    "meaning": "Irish origin, meaning 'strength' or 'exalted one'"
  },
  {
    "name": "Caoimhe",
    "meaning": "Irish origin, meaning 'gentle' or 'beautiful'"
  },
  {
    "name": "Deirdre",
    "meaning": "Irish origin, meaning 'broken-hearted' or 'oak grove'"
  },
  {
    "name": "Eilidh",
    "meaning": "Scottish Gaelic origin, meaning 'bright' or 'radiant'"
  },
  {
    "name": "Fionnuala",
    "meaning": "Irish origin, meaning 'fair shoulders'"
  },
  {
    "name": "Grainne",
    "meaning": "Irish origin, meaning 'grain' or 'love'"
  },
  {
    "name": "Muireann",
    "meaning": "Irish origin, meaning 'sea white' or 'sea fair'"
  },
  {
    "name": "Niamh",
    "meaning": "Irish origin, meaning 'bright'"
  },
  {
    "name": "Orla",
    "meaning": "Irish origin, meaning 'golden princess'"
  },
  {
    "name": "Roisin",
    "meaning": "Irish origin, meaning 'little rose'"
  },
  {
    "name": "Saoirse",
    "meaning": "Irish origin, meaning 'freedom'"
  },
  {
    "name": "Siobhan",
    "meaning": "Irish origin, meaning 'God is gracious'"
  },
  {
    "name": "Sinead",
    "meaning": "Irish origin, meaning 'God is gracious'"
  },
  {
    "name": "Una",
    "meaning": "Irish origin, meaning 'lamb' or 'one'"
  },
  {
    "name": "Blodwen",
    "meaning": "Welsh origin, meaning 'white flowers'"
  },
  {
    "name": "Branwen",
    "meaning": "Welsh origin, meaning 'white raven'"
  },
  {
    "name": "Carys",
    "meaning": "Welsh origin, meaning 'love'"
  },
  {
    "name": "Cerys",
    "meaning": "Welsh origin, meaning 'love'"
  },
  {
    "name": "Myfanwy",
    "meaning": "Welsh origin, meaning 'my rare one'"
  },
  {
    "name": "Rhiannon",
    "meaning": "Welsh origin, meaning 'great queen' or 'goddess'"
  },
  {
    "name": "Seren",
    "meaning": "Welsh origin, meaning 'star'"
  },
  {
    "name": "Ffion",
    "meaning": "Welsh origin, meaning 'foxglove'"
  },
  {
    "name": "Angharad",
    "meaning": "Welsh origin, meaning 'much loved'"
  },
  {
    "name": "Morwenna",
    "meaning": "Welsh and Cornish origin, meaning 'maiden'"
  },
  {
    "name": "Rowena",
    "meaning": "Celtic origin, meaning 'white mane'"
  },
  {
    "name": "Astrid",
    "meaning": "Old Norse origin, meaning 'divinely beautiful'"
  },
  {
    "name": "Ragnhild",
    "meaning": "Old Norse origin, meaning 'battle ruler'"
  },
  {
    "name": "Sigrid",
    "meaning": "Old Norse origin, meaning 'fair victory'"
  },
  {
    "name": "Ingrid",
    "meaning": "Old Norse origin, meaning 'fair' and 'Ing's beauty'"
  },
  {
    "name": "Brynhild",
    "meaning": "Old Norse origin, meaning 'armored warrior woman'"
  },
  {
    "name": "Gunhild",
    "meaning": "Old Norse origin, meaning 'battle warrior'"
  },
  {
    "name": "Gudrun",
    "meaning": "Old Norse origin, meaning 'God's rune'"
  },
  {
    "name": "Randi",
    "meaning": "Old Norse origin, meaning 'shield rim'"
  },
  {
    "name": "Solveig",
    "meaning": "Old Norse origin, meaning 'strong house'"
  },
  {
    "name": "Thora",
    "meaning": "Old Norse origin, meaning 'thunder'"
  },
  {
    "name": "Vigdis",
    "meaning": "Old Norse origin, meaning 'war goddess'"
  },
  {
    "name": "Alfhild",
    "meaning": "Old Norse origin, meaning 'elf battle'"
  },
  {
    "name": "Bodil",
    "meaning": "Old Norse origin, meaning 'remedy' or 'battle'"
  },
  {
    "name": "Dagny",
    "meaning": "Old Norse origin, meaning 'new day'"
  },
  {
    "name": "Eira",
    "meaning": "Welsh and Old Norse origin, meaning 'snow' or 'mercy'"
  },
  {
    "name": "Frida",
    "meaning": "Old Norse origin, meaning 'peace' or 'beautiful'"
  },
  {
    "name": "Helga",
    "meaning": "Old Norse origin, meaning 'holy' or 'blessed'"
  },
  {
    "name": "Hilde",
    "meaning": "Old Norse origin, meaning 'battle'"
  },
  {
    "name": "Runa",
    "meaning": "Old Norse origin, meaning 'secret lore' or 'rune'"
  },
  {
    "name": "Sigyn",
    "meaning": "Old Norse origin, meaning 'victorious girlfriend'"
  },
  {
    "name": "Thyra",
    "meaning": "Old Norse origin, meaning 'Thor's fighter'"
  },
  {
    "name": "Ulrika",
    "meaning": "Old Norse origin, meaning 'wolf ruler'"
  },
  {
    "name": "Valdis",
    "meaning": "Old Norse origin, meaning 'goddess of the dead'"
  },
  {
    "name": "Leila",
    "meaning": "Arabic origin, meaning 'night' or 'dark beauty'"
  },
  {
    "name": "Aisha",
    "meaning": "Arabic origin, meaning 'she who lives' or 'alive'"
  },
  {
    "name": "Fatima",
    "meaning": "Arabic origin, meaning 'abstaining'"
  },
  {
    "name": "Amira",
    "meaning": "Arabic origin, meaning 'princess' or 'commander'"
  },
  {
    "name": "Sana",
    "meaning": "Arabic origin, meaning 'brightness' or 'brilliance'"
  },
  {
    "name": "Nadia",
    "meaning": "Slavic and Arabic origin, meaning 'hope'"
  },
  {
    "name": "Dina",
    "meaning": "Arabic origin, meaning 'religious'"
  },
  {
    "name": "Rania",
    "meaning": "Arabic origin, meaning 'to gaze' or 'queen'"
  },
  {
    "name": "Yasmin",
    "meaning": "Persian origin, from the jasmine flower"
  },
  {
    "name": "Zahra",
    "meaning": "Arabic origin, meaning 'flower' or 'bright'"
  },
  {
    "name": "Nour",
    "meaning": "Arabic origin, meaning 'light'"
  },
  {
    "name": "Hind",
    "meaning": "Arabic origin, meaning 'India' or 'group of camels'"
  },
  {
    "name": "Maha",
    "meaning": "Arabic origin, meaning 'oryx' or 'beautiful eyes'"
  },
  {
    "name": "Maysa",
    "meaning": "Arabic origin, meaning 'to walk with a proud gait'"
  },
  {
    "name": "Noura",
    "meaning": "Arabic origin, meaning 'light' or 'luminous'"
  },
  {
    "name": "Rana",
    "meaning": "Arabic origin, meaning 'beautiful object'"
  },
  {
    "name": "Rima",
    "meaning": "Arabic origin, meaning 'white antelope'"
  },
  {
    "name": "Salma",
    "meaning": "Arabic origin, meaning 'peaceful'"
  },
  {
    "name": "Samira",
    "meaning": "Arabic origin, meaning 'entertainer'"
  },
  {
    "name": "Shirin",
    "meaning": "Persian origin, meaning 'sweet' or 'pleasant'"
  },
  {
    "name": "Soraya",
    "meaning": "Persian origin, meaning 'the Pleiades'"
  },
  {
    "name": "Zainab",
    "meaning": "Arabic origin, from a fragrant tree"
  },
  {
    "name": "Zara",
    "meaning": "Arabic and Hebrew origin, meaning 'blooming flower'"
  },
  {
    "name": "Hana",
    "meaning": "Arabic, Japanese, and Czech origin, meaning 'happiness'"
  },
  {
    "name": "Lubna",
    "meaning": "Arabic origin, meaning 'storax tree'"
  },
  {
    "name": "Maryam",
    "meaning": "Arabic form of Mary, meaning 'beloved'"
  },
  {
    "name": "Adina",
    "meaning": "Hebrew origin, meaning 'delicate' or 'gentle'"
  },
  {
    "name": "Avital",
    "meaning": "Hebrew origin, meaning 'father of dew'"
  },
  {
    "name": "Batya",
    "meaning": "Hebrew origin, meaning 'daughter of God'"
  },
  {
    "name": "Chava",
    "meaning": "Hebrew origin, meaning 'life'"
  },
  {
    "name": "Dalia",
    "meaning": "Hebrew origin, meaning 'gentle' or 'slender branch'"
  },
  {
    "name": "Devorah",
    "meaning": "Hebrew origin, meaning 'bee'"
  },
  {
    "name": "Elisheva",
    "meaning": "Hebrew origin, meaning 'my God is an oath'"
  },
  {
    "name": "Galya",
    "meaning": "Hebrew origin, meaning 'God has redeemed'"
  },
  {
    "name": "Hila",
    "meaning": "Hebrew origin, meaning 'halo' or 'praise'"
  },
  {
    "name": "Ilana",
    "meaning": "Hebrew origin, meaning 'oak tree'"
  },
  {
    "name": "Keren",
    "meaning": "Hebrew origin, meaning 'ray of light'"
  },
  {
    "name": "Liora",
    "meaning": "Hebrew origin, meaning 'I have light'"
  },
  {
    "name": "Michal",
    "meaning": "Hebrew origin, meaning 'who is like God?'"
  },
  {
    "name": "Nava",
    "meaning": "Hebrew origin, meaning 'beautiful' or 'pleasant'"
  },
  {
    "name": "Noa",
    "meaning": "Hebrew origin, meaning 'motion' or 'movement'"
  },
  {
    "name": "Ora",
    "meaning": "Hebrew origin, meaning 'light'"
  },
  {
    "name": "Orly",
    "meaning": "Hebrew origin, meaning 'my light'"
  },
  {
    "name": "Rina",
    "meaning": "Hebrew origin, meaning 'joy' or 'song'"
  },
  {
    "name": "Rivka",
    "meaning": "Hebrew origin, meaning 'to bind'"
  },
  {
    "name": "Shlomit",
    "meaning": "Hebrew origin, meaning 'peaceful'"
  },
  {
    "name": "Tali",
    "meaning": "Hebrew origin, meaning 'morning dew'"
  },
  {
    "name": "Tamar",
    "meaning": "Hebrew origin, meaning 'date palm'"
  },
  {
    "name": "Tikva",
    "meaning": "Hebrew origin, meaning 'hope'"
  },
  {
    "name": "Yael",
    "meaning": "Hebrew origin, meaning 'mountain goat'"
  },
  {
    "name": "Yehudit",
    "meaning": "Hebrew origin, meaning 'praised'"
  },
  {
    "name": "Zahava",
    "meaning": "Hebrew origin, meaning 'golden'"
  },
  {
    "name": "Lucia",
    "meaning": "Latin origin, meaning 'light'"
  },
  {
    "name": "Cecilia",
    "meaning": "Latin origin, meaning 'blind'"
  },
  {
    "name": "Clara",
    "meaning": "Latin origin, meaning 'clear' or 'bright'"
  },
  {
    "name": "Augusta",
    "meaning": "Latin origin, meaning 'great' or 'venerable'"
  },
  {
    "name": "Aurelia",
    "meaning": "Latin origin, meaning 'golden'"
  },
  {
    "name": "Beatrix",
    "meaning": "Latin origin, meaning 'she who brings happiness'"
  },
  {
    "name": "Camilla",
    "meaning": "Latin origin, meaning 'helper to the priest'"
  },
  {
    "name": "Claudia",
    "meaning": "Latin origin, meaning 'lame'"
  },
  {
    "name": "Cornelia",
    "meaning": "Latin origin, meaning 'horn'"
  },
  {
    "name": "Emilia",
    "meaning": "Latin origin, meaning 'rival' or 'industrious'"
  },
  {
    "name": "Flavia",
    "meaning": "Latin origin, meaning 'golden-haired'"
  },
  {
    "name": "Felicia",
    "meaning": "Latin origin, meaning 'happy' or 'fortunate'"
  },
  {
    "name": "Florentia",
    "meaning": "Latin origin, meaning 'flowering'"
  },
  {
    "name": "Honoria",
    "meaning": "Latin origin, meaning 'honor'"
  },
  {
    "name": "Lavinia",
    "meaning": "Latin origin, possibly meaning 'purity'"
  },
  {
    "name": "Livia",
    "meaning": "Latin origin, meaning 'blue-gray' or 'olive'"
  },
  {
    "name": "Maxima",
    "meaning": "Latin origin, meaning 'greatest'"
  },
  {
    "name": "Octavia",
    "meaning": "Latin origin, meaning 'eighth'"
  },
  {
    "name": "Portia",
    "meaning": "Latin origin, from the Roman Porcius family"
  },
  {
    "name": "Quintilla",
    "meaning": "Latin origin, meaning 'fifth'"
  },
  {
    "name": "Regina",
    "meaning": "Latin origin, meaning 'queen'"
  },
  {
    "name": "Serena",
    "meaning": "Latin origin, meaning 'serene' or 'peaceful'"
  },
  {
    "name": "Silvia",
    "meaning": "Latin origin, meaning 'forest'"
  },
  {
    "name": "Ursula",
    "meaning": "Latin origin, meaning 'little bear'"
  },
  {
    "name": "Valeria",
    "meaning": "Latin origin, meaning 'strong' or 'healthy'"
  },
  {
    "name": "Virginia",
    "meaning": "Latin origin, meaning 'pure'"
  },
  {
    "name": "Vivian",
    "meaning": "Latin origin, meaning 'alive'"
  },
  {
    "name": "Agatha",
    "meaning": "Greek origin, meaning 'good' or 'kind'"
  },
  {
    "name": "Alexandra",
    "meaning": "Greek origin, meaning 'defender of men'"
  },
  {
    "name": "Alexia",
    "meaning": "Greek origin, meaning 'defender'"
  },
  {
    "name": "Anastasia",
    "meaning": "Greek origin, meaning 'resurrection'"
  },
  {
    "name": "Andromache",
    "meaning": "Greek origin, meaning 'battle of men'"
  },
  {
    "name": "Andromeda",
    "meaning": "Greek origin, meaning 'ruler of men'"
  },
  {
    "name": "Angelica",
    "meaning": "Latin and Greek origin, meaning 'angelic'"
  },
  {
    "name": "Arete",
    "meaning": "Greek origin, meaning 'virtue' or 'excellence'"
  },
  {
    "name": "Ariadne",
    "meaning": "Greek origin, meaning 'most holy'"
  },
  {
    "name": "Calliope",
    "meaning": "Greek origin, meaning 'beautiful voice'"
  },
  {
    "name": "Callisto",
    "meaning": "Greek origin, meaning 'most beautiful'"
  },
  {
    "name": "Calypso",
    "meaning": "Greek origin, meaning 'she who conceals'"
  },
  {
    "name": "Chrysanthemum",
    "meaning": "Greek origin, meaning 'golden flower'"
  },
  {
    "name": "Cleopatra",
    "meaning": "Greek origin, meaning 'glory of the father'"
  },
  {
    "name": "Clio",
    "meaning": "Greek origin, meaning 'glory'"
  },
  {
    "name": "Delia",
    "meaning": "Greek origin, meaning 'from Delos'"
  },
  {
    "name": "Despina",
    "meaning": "Greek origin, meaning 'lady' or 'mistress'"
  },
  {
    "name": "Dorothea",
    "meaning": "Greek origin, meaning 'gift of God'"
  },
  {
    "name": "Eleni",
    "meaning": "Greek origin, meaning 'bright' or 'shining'"
  },
  {
    "name": "Eudora",
    "meaning": "Greek origin, meaning 'good gift'"
  },
  {
    "name": "Eudoxia",
    "meaning": "Greek origin, meaning 'good fame'"
  },
  {
    "name": "Eulalia",
    "meaning": "Greek origin, meaning 'sweet-speaking'"
  },
  {
    "name": "Euphemia",
    "meaning": "Greek origin, meaning 'well-spoken'"
  },
  {
    "name": "Euridyce",
    "meaning": "Greek origin, meaning 'wide justice'"
  },
  {
    "name": "Evangeline",
    "meaning": "Greek origin, meaning 'bearer of good news'"
  },
  {
    "name": "Georgia",
    "meaning": "Greek origin, meaning 'farmer'"
  },
  {
    "name": "Helena",
    "meaning": "Greek origin, meaning 'bright' or 'shining'"
  },
  {
    "name": "Hermione",
    "meaning": "Greek origin, meaning 'messenger'"
  },
  {
    "name": "Iphigenia",
    "meaning": "Greek origin, meaning 'strong-born'"
  },
  {
    "name": "Kallisto",
    "meaning": "Greek origin, meaning 'most beautiful'"
  },
  {
    "name": "Katerina",
    "meaning": "Greek origin, meaning 'pure'"
  },
  {
    "name": "Kyria",
    "meaning": "Greek origin, meaning 'lady'"
  },
  {
    "name": "Larissa",
    "meaning": "Greek origin, from the city of Larissa"
  },
  {
    "name": "Lyra",
    "meaning": "Greek origin, meaning 'lyre'"
  },
  {
    "name": "Melanie",
    "meaning": "Greek origin, meaning 'dark' or 'black'"
  },
  {
    "name": "Melissa",
    "meaning": "Greek origin, meaning 'honey bee'"
  },
  {
    "name": "Melpomene",
    "meaning": "Greek origin, meaning 'to celebrate with song'"
  },
  {
    "name": "Nausicaa",
    "meaning": "Greek origin, meaning 'burner of ships'"
  },
  {
    "name": "Niobe",
    "meaning": "Greek origin, meaning 'fern'"
  },
  {
    "name": "Olympia",
    "meaning": "Greek origin, meaning 'from Mount Olympus'"
  },
  {
    "name": "Phoibos",
    "meaning": "Greek origin, meaning 'bright'"
  },
  {
    "name": "Polyxena",
    "meaning": "Greek origin, meaning 'hospitality'"
  },
  {
    "name": "Rhea",
    "meaning": "Greek origin, meaning 'flowing' or 'earth'"
  },
  {
    "name": "Sophia",
    "meaning": "Greek origin, meaning 'wisdom'"
  },
  {
    "name": "Tethys",
    "meaning": "Greek origin, name of a Titan ocean goddess"
  },
  {
    "name": "Thea",
    "meaning": "Greek origin, meaning 'goddess' or 'gift of God'"
  },
  {
    "name": "Theodosia",
    "meaning": "Greek origin, meaning 'giving to God'"
  },
  {
    "name": "Xanthippe",
    "meaning": "Greek origin, meaning 'yellow horse'"
  },
  {
    "name": "Xenia",
    "meaning": "Greek origin, meaning 'hospitality'"
  },
  {
    "name": "Zephyrine",
    "meaning": "Greek origin, from Zephyrus, the west wind"
  },
  {
    "name": "Amara",
    "meaning": "Igbo and Swahili origin, meaning 'grace' or 'eternal'"
  },
  {
    "name": "Adaeze",
    "meaning": "Igbo origin, meaning 'daughter of the king'"
  },
  {
    "name": "Adanna",
    "meaning": "Igbo origin, meaning 'father's daughter'"
  },
  {
    "name": "Adaora",
    "meaning": "Igbo origin, meaning 'daughter of the people'"
  },
  {
    "name": "Adeola",
    "meaning": "Yoruba origin, meaning 'crown brings honor'"
  },
  {
    "name": "Amaka",
    "meaning": "Igbo origin, meaning 'grace is good'"
  },
  {
    "name": "Amara",
    "meaning": "Igbo origin, meaning 'grace'"
  },
  {
    "name": "Amirah",
    "meaning": "Arabic and Swahili origin, meaning 'princess'"
  },
  {
    "name": "Asha",
    "meaning": "Swahili and Sanskrit origin, meaning 'life' or 'hope'"
  },
  {
    "name": "Asante",
    "meaning": "Swahili origin, meaning 'thankful'"
  },
  {
    "name": "Ayasha",
    "meaning": "Native American and Arabic origin, meaning 'little one'"
  },
  {
    "name": "Adaeze",
    "meaning": "Igbo origin, meaning 'princess'"
  },
  {
    "name": "Chiamaka",
    "meaning": "Igbo origin, meaning 'God is beautiful'"
  },
  {
    "name": "Chidinma",
    "meaning": "Igbo origin, meaning 'God is good'"
  },
  {
    "name": "Chinwe",
    "meaning": "Igbo origin, meaning 'God owns'"
  },
  {
    "name": "Chioma",
    "meaning": "Igbo origin, meaning 'good God'"
  },
  {
    "name": "Dalila",
    "meaning": "Swahili origin, meaning 'gentle'"
  },
  {
    "name": "Fatoumata",
    "meaning": "West African form of Fatima"
  },
  {
    "name": "Fatou",
    "meaning": "West African form of Fatima, meaning 'abstaining'"
  },
  {
    "name": "Habiba",
    "meaning": "Arabic and Swahili origin, meaning 'beloved'"
  },
  {
    "name": "Imani",
    "meaning": "Swahili origin, meaning 'faith'"
  },
  {
    "name": "Ife",
    "meaning": "Yoruba origin, meaning 'love'"
  },
  {
    "name": "Jamila",
    "meaning": "Arabic and Swahili origin, meaning 'beautiful'"
  },
  {
    "name": "Jelena",
    "meaning": "South Slavic form of Helen, meaning 'bright'"
  },
  {
    "name": "Kamili",
    "meaning": "Swahili origin, meaning 'perfect'"
  },
  {
    "name": "Kefilwe",
    "meaning": "Tswana origin, meaning 'I have been given'"
  },
  {
    "name": "Kemi",
    "meaning": "Yoruba origin, meaning 'God cares for me'"
  },
  {
    "name": "Lola",
    "meaning": "Spanish and Yoruba origin, meaning 'rich honor'"
  },
  {
    "name": "Makena",
    "meaning": "Kikuyu origin, meaning 'happy one'"
  },
  {
    "name": "Nkiruka",
    "meaning": "Igbo origin, meaning 'the future is greater'"
  },
  {
    "name": "Nneoma",
    "meaning": "Igbo origin, meaning 'good mother'"
  },
  {
    "name": "Nomsa",
    "meaning": "Zulu origin, meaning 'mother of kindness'"
  },
  {
    "name": "Nthabi",
    "meaning": "Sotho origin, meaning 'one who makes happy'"
  },
  {
    "name": "Olu",
    "meaning": "Yoruba origin, meaning 'the supreme'"
  },
  {
    "name": "Patience",
    "meaning": "Latin origin, meaning 'patience'"
  },
  {
    "name": "Rejoice",
    "meaning": "English virtue name meaning 'to feel joy'"
  },
  {
    "name": "Sade",
    "meaning": "Yoruba origin, meaning 'honor earns a crown'"
  },
  {
    "name": "Safiya",
    "meaning": "Arabic and Swahili origin, meaning 'pure'"
  },
  {
    "name": "Sena",
    "meaning": "Hausa origin, meaning 'world news'"
  },
  {
    "name": "Thandiwe",
    "meaning": "Zulu origin, meaning 'beloved'"
  },
  {
    "name": "Wanjiru",
    "meaning": "Kikuyu origin, meaning 'born near the fig tree'"
  },
  {
    "name": "Yewande",
    "meaning": "Yoruba origin, meaning 'mother has come back'"
  },
  {
    "name": "Zola",
    "meaning": "African and Italian origin, meaning 'quiet' or 'calm'"
  },
  {
    "name": "Zuri",
    "meaning": "Swahili origin, meaning 'beautiful'"
  },
  {
    "name": "Priya",
    "meaning": "Sanskrit origin, meaning 'beloved' or 'dear'"
  },
  {
    "name": "Ananya",
    "meaning": "Sanskrit origin, meaning 'unique' or 'incomparable'"
  },
  {
    "name": "Anjali",
    "meaning": "Sanskrit origin, meaning 'offering' or 'salutation'"
  },
  {
    "name": "Anushka",
    "meaning": "Sanskrit origin, meaning 'grace' or 'favor'"
  },
  {
    "name": "Asha",
    "meaning": "Sanskrit origin, meaning 'hope' or 'wish'"
  },
  {
    "name": "Devi",
    "meaning": "Sanskrit origin, meaning 'goddess'"
  },
  {
    "name": "Divya",
    "meaning": "Sanskrit origin, meaning 'divine' or 'brilliant'"
  },
  {
    "name": "Durga",
    "meaning": "Sanskrit origin, name of the warrior goddess"
  },
  {
    "name": "Gayatri",
    "meaning": "Sanskrit origin, meaning 'song' or 'hymn'"
  },
  {
    "name": "Geeta",
    "meaning": "Sanskrit origin, meaning 'song'"
  },
  {
    "name": "Indira",
    "meaning": "Sanskrit origin, meaning 'beauty' or 'splendid'"
  },
  {
    "name": "Jaya",
    "meaning": "Sanskrit origin, meaning 'victory'"
  },
  {
    "name": "Kamala",
    "meaning": "Sanskrit origin, meaning 'lotus'"
  },
  {
    "name": "Kiran",
    "meaning": "Sanskrit origin, meaning 'ray of light'"
  },
  {
    "name": "Lakshmi",
    "meaning": "Sanskrit origin, meaning 'good omen' or 'wealth'"
  },
  {
    "name": "Lalita",
    "meaning": "Sanskrit origin, meaning 'playful' or 'charming'"
  },
  {
    "name": "Leela",
    "meaning": "Sanskrit origin, meaning 'divine play'"
  },
  {
    "name": "Malini",
    "meaning": "Sanskrit origin, meaning 'sweet-smelling' or 'gardener'"
  },
  {
    "name": "Meera",
    "meaning": "Sanskrit origin, meaning 'sea' or 'ocean'"
  },
  {
    "name": "Nisha",
    "meaning": "Sanskrit origin, meaning 'night'"
  },
  {
    "name": "Padma",
    "meaning": "Sanskrit origin, meaning 'lotus'"
  },
  {
    "name": "Parvati",
    "meaning": "Sanskrit origin, meaning 'daughter of the mountain'"
  },
  {
    "name": "Pooja",
    "meaning": "Sanskrit origin, meaning 'worship' or 'prayer'"
  },
  {
    "name": "Radha",
    "meaning": "Sanskrit origin, meaning 'success' or 'devotion'"
  },
  {
    "name": "Rekha",
    "meaning": "Sanskrit origin, meaning 'line'"
  },
  {
    "name": "Ritu",
    "meaning": "Sanskrit origin, meaning 'season'"
  },
  {
    "name": "Saraswati",
    "meaning": "Sanskrit origin, name of goddess of knowledge"
  },
  {
    "name": "Shalini",
    "meaning": "Sanskrit origin, meaning 'modest'"
  },
  {
    "name": "Shanti",
    "meaning": "Sanskrit origin, meaning 'peace'"
  },
  {
    "name": "Shweta",
    "meaning": "Sanskrit origin, meaning 'white' or 'pure'"
  },
  {
    "name": "Sita",
    "meaning": "Sanskrit origin, meaning 'furrow' or 'wife of Ram'"
  },
  {
    "name": "Sunita",
    "meaning": "Sanskrit origin, meaning 'well-conducted'"
  },
  {
    "name": "Urvashi",
    "meaning": "Sanskrit origin, name of a celestial nymph"
  },
  {
    "name": "Vandana",
    "meaning": "Sanskrit origin, meaning 'salutation' or 'worship'"
  },
  {
    "name": "Varsha",
    "meaning": "Sanskrit origin, meaning 'rain'"
  },
  {
    "name": "Vidya",
    "meaning": "Sanskrit origin, meaning 'knowledge'"
  },
  {
    "name": "Vimala",
    "meaning": "Sanskrit origin, meaning 'pure' or 'clean'"
  },
  {
    "name": "Hana",
    "meaning": "Japanese origin, meaning 'flower' or 'blossom'"
  },
  {
    "name": "Sakura",
    "meaning": "Japanese origin, meaning 'cherry blossom'"
  },
  {
    "name": "Yuki",
    "meaning": "Japanese origin, meaning 'snow' or 'happiness'"
  },
  {
    "name": "Ai",
    "meaning": "Japanese origin, meaning 'love' or 'indigo'"
  },
  {
    "name": "Aiko",
    "meaning": "Japanese origin, meaning 'beloved child'"
  },
  {
    "name": "Akemi",
    "meaning": "Japanese origin, meaning 'bright beauty'"
  },
  {
    "name": "Akiko",
    "meaning": "Japanese origin, meaning 'autumn child'"
  },
  {
    "name": "Amaya",
    "meaning": "Japanese origin, meaning 'night rain'"
  },
  {
    "name": "Asuka",
    "meaning": "Japanese origin, meaning 'fragrance' or 'tomorrow'"
  },
  {
    "name": "Ayaka",
    "meaning": "Japanese origin, meaning 'colorful flower'"
  },
  {
    "name": "Ayame",
    "meaning": "Japanese origin, meaning 'iris flower'"
  },
  {
    "name": "Chiaki",
    "meaning": "Japanese origin, meaning 'thousand autumns'"
  },
  {
    "name": "Emiko",
    "meaning": "Japanese origin, meaning 'beautiful child'"
  },
  {
    "name": "Fumiko",
    "meaning": "Japanese origin, meaning 'child of beautiful wealth'"
  },
  {
    "name": "Haruka",
    "meaning": "Japanese origin, meaning 'distant' or 'spring flower'"
  },
  {
    "name": "Haruko",
    "meaning": "Japanese origin, meaning 'spring child'"
  },
  {
    "name": "Himari",
    "meaning": "Japanese origin, meaning 'sunflower'"
  },
  {
    "name": "Hinata",
    "meaning": "Japanese origin, meaning 'toward the sun'"
  },
  {
    "name": "Hiromi",
    "meaning": "Japanese origin, meaning 'widespread beauty'"
  },
  {
    "name": "Ichika",
    "meaning": "Japanese origin, meaning 'one summer flower'"
  },
  {
    "name": "Kaede",
    "meaning": "Japanese origin, meaning 'maple'"
  },
  {
    "name": "Kaori",
    "meaning": "Japanese origin, meaning 'fragrance'"
  },
  {
    "name": "Keiko",
    "meaning": "Japanese origin, meaning 'blessing child'"
  },
  {
    "name": "Kimi",
    "meaning": "Japanese origin, meaning 'noble' or 'righteous'"
  },
  {
    "name": "Koharu",
    "meaning": "Japanese origin, meaning 'little spring'"
  },
  {
    "name": "Kotone",
    "meaning": "Japanese origin, meaning 'sound of the koto'"
  },
  {
    "name": "Kumiko",
    "meaning": "Japanese origin, meaning 'long-time beautiful child'"
  },
  {
    "name": "Kyo",
    "meaning": "Japanese origin, meaning 'capital city'"
  },
  {
    "name": "Kyoko",
    "meaning": "Japanese origin, meaning 'mirror' or 'apricot'"
  },
  {
    "name": "Madoka",
    "meaning": "Japanese origin, meaning 'circle' or 'gentle'"
  },
  {
    "name": "Mai",
    "meaning": "Japanese origin, meaning 'dance'"
  },
  {
    "name": "Maiko",
    "meaning": "Japanese origin, meaning 'dance child'"
  },
  {
    "name": "Mako",
    "meaning": "Japanese origin, meaning 'truth' or 'genuine'"
  },
  {
    "name": "Manami",
    "meaning": "Japanese origin, meaning 'love of the sea'"
  },
  {
    "name": "Masako",
    "meaning": "Japanese origin, meaning 'correct child'"
  },
  {
    "name": "Michiko",
    "meaning": "Japanese origin, meaning 'child of the way'"
  },
  {
    "name": "Midori",
    "meaning": "Japanese origin, meaning 'green'"
  },
  {
    "name": "Miho",
    "meaning": "Japanese origin, meaning 'beautiful sail'"
  },
  {
    "name": "Mika",
    "meaning": "Japanese and Hebrew origin, meaning 'beautiful fragrance'"
  },
  {
    "name": "Minako",
    "meaning": "Japanese origin, meaning 'beautiful child'"
  },
  {
    "name": "Minami",
    "meaning": "Japanese origin, meaning 'south'"
  },
  {
    "name": "Misaki",
    "meaning": "Japanese origin, meaning 'beautiful blossom'"
  },
  {
    "name": "Mitsuki",
    "meaning": "Japanese origin, meaning 'beautiful moon'"
  },
  {
    "name": "Miyuki",
    "meaning": "Japanese origin, meaning 'beautiful happiness'"
  },
  {
    "name": "Momoko",
    "meaning": "Japanese origin, meaning 'peach child'"
  },
  {
    "name": "Nanami",
    "meaning": "Japanese origin, meaning 'seven seas'"
  },
  {
    "name": "Naomi",
    "meaning": "Hebrew and Japanese origin, meaning 'beautiful' or 'pleasantness'"
  },
  {
    "name": "Natsuki",
    "meaning": "Japanese origin, meaning 'summer hope'"
  },
  {
    "name": "Natsumi",
    "meaning": "Japanese origin, meaning 'summer beauty'"
  },
  {
    "name": "Noriko",
    "meaning": "Japanese origin, meaning 'law child'"
  },
  {
    "name": "Rei",
    "meaning": "Japanese origin, meaning 'lovely' or 'zero'"
  },
  {
    "name": "Reiko",
    "meaning": "Japanese origin, meaning 'gratitude child'"
  },
  {
    "name": "Ren",
    "meaning": "Japanese origin, meaning 'lotus' or 'love'"
  },
  {
    "name": "Rina",
    "meaning": "Japanese origin, meaning 'white jasmine'"
  },
  {
    "name": "Risa",
    "meaning": "Japanese origin, meaning 'sand' or 'village'"
  },
  {
    "name": "Ritsuko",
    "meaning": "Japanese origin, meaning 'law child'"
  },
  {
    "name": "Ryoko",
    "meaning": "Japanese origin, meaning 'refreshing child'"
  },
  {
    "name": "Saki",
    "meaning": "Japanese origin, meaning 'blossom' or 'hope'"
  },
  {
    "name": "Satomi",
    "meaning": "Japanese origin, meaning 'beautiful wisdom'"
  },
  {
    "name": "Satsuki",
    "meaning": "Japanese origin, meaning 'May flower'"
  },
  {
    "name": "Sayuri",
    "meaning": "Japanese origin, meaning 'small lily'"
  },
  {
    "name": "Shizuka",
    "meaning": "Japanese origin, meaning 'quiet' or 'calm'"
  },
  {
    "name": "Sora",
    "meaning": "Japanese origin, meaning 'sky'"
  },
  {
    "name": "Sumire",
    "meaning": "Japanese origin, meaning 'violet flower'"
  },
  {
    "name": "Tamako",
    "meaning": "Japanese origin, meaning 'jewel child'"
  },
  {
    "name": "Tomoko",
    "meaning": "Japanese origin, meaning 'friendly child'"
  },
  {
    "name": "Tsubaki",
    "meaning": "Japanese origin, meaning 'camellia flower'"
  },
  {
    "name": "Tsukiko",
    "meaning": "Japanese origin, meaning 'moonlight child'"
  },
  {
    "name": "Umi",
    "meaning": "Japanese origin, meaning 'sea'"
  },
  {
    "name": "Yoko",
    "meaning": "Japanese origin, meaning 'positive child'"
  },
  {
    "name": "Yoshiko",
    "meaning": "Japanese origin, meaning 'good child'"
  },
  {
    "name": "Yua",
    "meaning": "Japanese origin, meaning 'binding love'"
  },
  {
    "name": "Yui",
    "meaning": "Japanese origin, meaning 'binding' or 'reliant'"
  },
  {
    "name": "Yukari",
    "meaning": "Japanese origin, meaning 'related' or 'violet'"
  },
  {
    "name": "Yukiko",
    "meaning": "Japanese origin, meaning 'snow child'"
  },
  {
    "name": "Yume",
    "meaning": "Japanese origin, meaning 'dream'"
  },
  {
    "name": "Yumiko",
    "meaning": "Japanese origin, meaning 'reason beautiful child'"
  },
  {
    "name": "Yuri",
    "meaning": "Japanese origin, meaning 'lily'"
  },
  {
    "name": "Yuriko",
    "meaning": "Japanese origin, meaning 'lily child'"
  },
  {
    "name": "Sofia",
    "meaning": "Greek origin via Spanish, meaning 'wisdom'"
  },
  {
    "name": "Valentina",
    "meaning": "Latin origin, meaning 'strong' or 'healthy'"
  },
  {
    "name": "Camila",
    "meaning": "Latin origin, meaning 'helper to the priest'"
  },
  {
    "name": "Isabella",
    "meaning": "Hebrew origin via Italian, meaning 'devoted to God'"
  },
  {
    "name": "Daniela",
    "meaning": "Hebrew origin, meaning 'God is my judge'"
  },
  {
    "name": "Valeria",
    "meaning": "Latin origin, meaning 'strong'"
  },
  {
    "name": "Gabriela",
    "meaning": "Hebrew origin, meaning 'God is my strength'"
  },
  {
    "name": "Mariana",
    "meaning": "Latin origin, combining Mary and Ana"
  },
  {
    "name": "Luciana",
    "meaning": "Latin origin, meaning 'light'"
  },
  {
    "name": "Martina",
    "meaning": "Latin origin, meaning 'of Mars'"
  },
  {
    "name": "Adriana",
    "meaning": "Latin origin, meaning 'from Hadria'"
  },
  {
    "name": "Paola",
    "meaning": "Italian and Spanish form of Paula, meaning 'small'"
  },
  {
    "name": "Alejandra",
    "meaning": "Spanish form of Alexandra, meaning 'defender of men'"
  },
  {
    "name": "Catalina",
    "meaning": "Spanish form of Katherine, meaning 'pure'"
  },
  {
    "name": "Dolores",
    "meaning": "Spanish origin, meaning 'sorrows'"
  },
  {
    "name": "Esperanza",
    "meaning": "Spanish origin, meaning 'hope'"
  },
  {
    "name": "Guadalupe",
    "meaning": "Spanish origin, meaning 'valley of the wolf'"
  },
  {
    "name": "In\u00e9s",
    "meaning": "Spanish form of Agnes, meaning 'pure'"
  },
  {
    "name": "Leticia",
    "meaning": "Spanish origin, meaning 'joy'"
  },
  {
    "name": "Lupe",
    "meaning": "Spanish short form of Guadalupe"
  },
  {
    "name": "Mercedes",
    "meaning": "Spanish origin, meaning 'mercies'"
  },
  {
    "name": "Paloma",
    "meaning": "Spanish origin, meaning 'dove'"
  },
  {
    "name": "Pilar",
    "meaning": "Spanish origin, meaning 'pillar'"
  },
  {
    "name": "Rosario",
    "meaning": "Spanish origin, meaning 'rosary'"
  },
  {
    "name": "Soledad",
    "meaning": "Spanish origin, meaning 'solitude'"
  },
  {
    "name": "Ximena",
    "meaning": "Spanish form of Simona, meaning 'one who hears'"
  },
  {
    "name": "Yolanda",
    "meaning": "Greek and French origin, meaning 'violet flower'"
  },
  {
    "name": "Adele",
    "meaning": "Old Germanic origin, meaning 'noble'"
  },
  {
    "name": "Amelie",
    "meaning": "Old Germanic origin, meaning 'industrious'"
  },
  {
    "name": "Brigitte",
    "meaning": "Irish and French origin, meaning 'strength'"
  },
  {
    "name": "Camille",
    "meaning": "Latin origin, meaning 'young ceremonial attendant'"
  },
  {
    "name": "Cecile",
    "meaning": "French form of Cecilia, meaning 'blind'"
  },
  {
    "name": "Celeste",
    "meaning": "Latin and French origin, meaning 'heavenly'"
  },
  {
    "name": "Chantel",
    "meaning": "Old French origin, meaning 'stone' or 'song'"
  },
  {
    "name": "Christine",
    "meaning": "Latin origin, meaning 'follower of Christ'"
  },
  {
    "name": "Claudette",
    "meaning": "French diminutive of Claude, meaning 'lame'"
  },
  {
    "name": "Colette",
    "meaning": "French diminutive of Nicole, meaning 'victory'"
  },
  {
    "name": "Danielle",
    "meaning": "French form of Daniel, meaning 'God is my judge'"
  },
  {
    "name": "Elise",
    "meaning": "French form of Elizabeth, meaning 'God's promise'"
  },
  {
    "name": "Estelle",
    "meaning": "Old French and Latin origin, meaning 'star'"
  },
  {
    "name": "Flore",
    "meaning": "French form of Flora, meaning 'flower'"
  },
  {
    "name": "Francoise",
    "meaning": "French form of Frances, meaning 'Frenchwoman'"
  },
  {
    "name": "Genevieve",
    "meaning": "Celtic and Germanic origin, meaning 'tribe woman'"
  },
  {
    "name": "Helene",
    "meaning": "French form of Helen, meaning 'bright'"
  },
  {
    "name": "Isabelle",
    "meaning": "French form of Isabel, meaning 'devoted to God'"
  },
  {
    "name": "Jacqueline",
    "meaning": "French form of James, meaning 'supplanter'"
  },
  {
    "name": "Lisette",
    "meaning": "French diminutive of Elizabeth"
  },
  {
    "name": "Louisette",
    "meaning": "French diminutive of Louise"
  },
  {
    "name": "Lucie",
    "meaning": "French form of Lucy, meaning 'light'"
  },
  {
    "name": "Manon",
    "meaning": "French diminutive of Marie"
  },
  {
    "name": "Margot",
    "meaning": "French diminutive of Margaret, meaning 'pearl'"
  },
  {
    "name": "Marie",
    "meaning": "French form of Mary, meaning 'beloved'"
  },
  {
    "name": "Mathilde",
    "meaning": "French form of Matilda, meaning 'might battle'"
  },
  {
    "name": "Melodie",
    "meaning": "French form of Melody, meaning 'song'"
  },
  {
    "name": "Monique",
    "meaning": "French form of Monica, meaning 'adviser'"
  },
  {
    "name": "Nadege",
    "meaning": "French form of Nadezhda, meaning 'hope'"
  },
  {
    "name": "Nadine",
    "meaning": "French form of Nadia, meaning 'hope'"
  },
  {
    "name": "Nathalie",
    "meaning": "French form of Natalia, meaning 'born on Christmas'"
  },
  {
    "name": "Pauline",
    "meaning": "French form of Paula, meaning 'small'"
  },
  {
    "name": "Renee",
    "meaning": "French form of Renata, meaning 'reborn'"
  },
  {
    "name": "Suzette",
    "meaning": "French diminutive of Susan, meaning 'lily'"
  },
  {
    "name": "Sylvie",
    "meaning": "French form of Silvia, meaning 'forest'"
  },
  {
    "name": "Veronique",
    "meaning": "French form of Veronica, meaning 'she who brings victory'"
  },
  {
    "name": "Vivienne",
    "meaning": "French form of Vivian, meaning 'alive'"
  },
  {
    "name": "Yvette",
    "meaning": "French diminutive of Yvonne, meaning 'yew wood'"
  },
  {
    "name": "Yvonne",
    "meaning": "French origin, meaning 'yew wood'"
  },
  {
    "name": "Alessandra",
    "meaning": "Italian form of Alexandra, meaning 'defender of men'"
  },
  {
    "name": "Angelina",
    "meaning": "Italian form of Angela, meaning 'angel'"
  },
  {
    "name": "Beatrice",
    "meaning": "Italian form of Beatrix, meaning 'she who brings happiness'"
  },
  {
    "name": "Bianca",
    "meaning": "Italian origin, meaning 'white' or 'fair'"
  },
  {
    "name": "Chiara",
    "meaning": "Italian form of Clara, meaning 'clear' or 'bright'"
  },
  {
    "name": "Concetta",
    "meaning": "Italian origin, meaning 'immaculate conception'"
  },
  {
    "name": "Constanza",
    "meaning": "Italian form of Constance, meaning 'steadfast'"
  },
  {
    "name": "Darina",
    "meaning": "Irish and Slavic origin, meaning 'gift'"
  },
  {
    "name": "Elena",
    "meaning": "Italian and Spanish form of Helen, meaning 'bright'"
  },
  {
    "name": "Federica",
    "meaning": "Italian form of Frederica, meaning 'peaceful ruler'"
  },
  {
    "name": "Fiamma",
    "meaning": "Italian origin, meaning 'flame'"
  },
  {
    "name": "Filomena",
    "meaning": "Greek and Italian origin, meaning 'friend of strength'"
  },
  {
    "name": "Fiora",
    "meaning": "Italian form of Flora, meaning 'flower'"
  },
  {
    "name": "Fiorella",
    "meaning": "Italian diminutive of Flora, meaning 'little flower'"
  },
  {
    "name": "Flavia",
    "meaning": "Italian and Latin origin, meaning 'golden-haired'"
  },
  {
    "name": "Francesca",
    "meaning": "Italian form of Frances, meaning 'French woman'"
  },
  {
    "name": "Giovanna",
    "meaning": "Italian form of Johanna, meaning 'God is gracious'"
  },
  {
    "name": "Giuseppina",
    "meaning": "Italian form of Josephine"
  },
  {
    "name": "Graziella",
    "meaning": "Italian diminutive of Grazia, meaning 'grace'"
  },
  {
    "name": "Ilaria",
    "meaning": "Italian form of Hilaria, meaning 'cheerful'"
  },
  {
    "name": "Lorenza",
    "meaning": "Italian form of Laurentia, meaning 'from Laurentum'"
  },
  {
    "name": "Lucrezia",
    "meaning": "Italian form of Lucretia, meaning 'gain'"
  },
  {
    "name": "Luisa",
    "meaning": "Italian and Spanish form of Louise, meaning 'warrior'"
  },
  {
    "name": "Maddalena",
    "meaning": "Italian form of Magdalene, meaning 'from Magdala'"
  },
  {
    "name": "Margherita",
    "meaning": "Italian form of Margaret, meaning 'pearl'"
  },
  {
    "name": "Marianna",
    "meaning": "Italian combination of Maria and Anna"
  },
  {
    "name": "Natalia",
    "meaning": "Italian and Latin origin, meaning 'born on Christmas'"
  },
  {
    "name": "Nicoletta",
    "meaning": "Italian diminutive of Nicola"
  },
  {
    "name": "Ornella",
    "meaning": "Italian origin, meaning 'flowering ash tree'"
  },
  {
    "name": "Paola",
    "meaning": "Italian form of Paula, meaning 'small'"
  },
  {
    "name": "Raffaella",
    "meaning": "Italian form of Raphaela, meaning 'God has healed'"
  },
  {
    "name": "Roberta",
    "meaning": "Italian form of Roberta, meaning 'bright fame'"
  },
  {
    "name": "Rosa",
    "meaning": "Italian and Spanish form of Rose, meaning 'rose'"
  },
  {
    "name": "Rosaria",
    "meaning": "Italian origin, meaning 'rosary'"
  },
  {
    "name": "Rossana",
    "meaning": "Italian form of Roxanna, meaning 'dawn'"
  },
  {
    "name": "Simonetta",
    "meaning": "Italian diminutive of Simone"
  },
  {
    "name": "Stella",
    "meaning": "Italian and Latin origin, meaning 'star'"
  },
  {
    "name": "Teresa",
    "meaning": "Italian and Spanish form of Theresa, meaning 'harvest'"
  },
  {
    "name": "Valentina",
    "meaning": "Latin and Italian origin, meaning 'strong'"
  },
  {
    "name": "Vanessa",
    "meaning": "Invented by Jonathan Swift, from Esther Vanhomrigh"
  },
  {
    "name": "Viola",
    "meaning": "Italian and Latin origin, from the violet flower"
  },
  {
    "name": "Vittoria",
    "meaning": "Italian form of Victoria, meaning 'victory'"
  },
  {
    "name": "Anya",
    "meaning": "Russian form of Anna, meaning 'grace'"
  },
  {
    "name": "Dasha",
    "meaning": "Russian short form of Darya, meaning 'sea'"
  },
  {
    "name": "Inna",
    "meaning": "Russian origin, meaning 'strong water'"
  },
  {
    "name": "Irina",
    "meaning": "Russian form of Irene, meaning 'peace'"
  },
  {
    "name": "Katya",
    "meaning": "Russian form of Katherine, meaning 'pure'"
  },
  {
    "name": "Kseniya",
    "meaning": "Russian form of Xenia, meaning 'hospitality'"
  },
  {
    "name": "Larisa",
    "meaning": "Russian form of Larissa"
  },
  {
    "name": "Liliya",
    "meaning": "Russian form of Lily"
  },
  {
    "name": "Masha",
    "meaning": "Russian form of Maria, meaning 'beloved'"
  },
  {
    "name": "Milena",
    "meaning": "Slavic origin, meaning 'gracious' or 'dear'"
  },
  {
    "name": "Natasha",
    "meaning": "Russian form of Natalia, meaning 'born at Christmas'"
  },
  {
    "name": "Oksana",
    "meaning": "Ukrainian form of Xenia, meaning 'hospitality'"
  },
  {
    "name": "Olga",
    "meaning": "Russian and Scandinavian origin, meaning 'holy'"
  },
  {
    "name": "Sasha",
    "meaning": "Russian short form of Alexandra"
  },
  {
    "name": "Svetlana",
    "meaning": "Russian origin, meaning 'light' or 'pure'"
  },
  {
    "name": "Tatiana",
    "meaning": "Russian origin, meaning 'of the family of Tatianus'"
  },
  {
    "name": "Vanya",
    "meaning": "Russian diminutive form of Ivana"
  },
  {
    "name": "Vera",
    "meaning": "Russian and Slavic origin, meaning 'faith'"
  },
  {
    "name": "Zorya",
    "meaning": "Slavic origin, meaning 'dawn'"
  },
  {
    "name": "Zuzanna",
    "meaning": "Polish form of Susanna, meaning 'lily'"
  },
  {
    "name": "Zuzka",
    "meaning": "Slovak form of Susanna"
  },
  {
    "name": "Bozena",
    "meaning": "Czech and Polish origin, meaning 'divine'"
  },
  {
    "name": "Blanka",
    "meaning": "Czech and Polish form of Blanche, meaning 'white'"
  },
  {
    "name": "Dagmara",
    "meaning": "Polish origin, meaning 'day maid'"
  },
  {
    "name": "Dominika",
    "meaning": "Slavic form of Dominica, meaning 'belonging to God'"
  },
  {
    "name": "Ivana",
    "meaning": "Slavic form of Johanna, meaning 'God is gracious'"
  },
  {
    "name": "Karolina",
    "meaning": "Slavic form of Caroline, meaning 'free woman'"
  },
  {
    "name": "Ludmila",
    "meaning": "Slavic origin, meaning 'gracious people'"
  },
  {
    "name": "Magdalena",
    "meaning": "Slavic form of Magdalene, meaning 'from Magdala'"
  },
  {
    "name": "Petra",
    "meaning": "Greek and Slavic origin, meaning 'rock'"
  },
  {
    "name": "Radmila",
    "meaning": "Slavic origin, meaning 'hard-working'"
  },
  {
    "name": "Stanislava",
    "meaning": "Slavic origin, meaning 'glory of the camp'"
  },
  {
    "name": "Zdena",
    "meaning": "Czech short form of Zdenka"
  },
  {
    "name": "Zlata",
    "meaning": "Slavic origin, meaning 'golden'"
  },
  {
    "name": "Mabel",
    "meaning": "Latin origin, meaning 'lovable'"
  },
  {
    "name": "Gertrude",
    "meaning": "Old Germanic origin, meaning 'strength of spear'"
  },
  {
    "name": "Edith",
    "meaning": "Old English origin, meaning 'prosperous in war'"
  },
  {
    "name": "Agnes",
    "meaning": "Greek origin, meaning 'pure' or 'holy'"
  },
  {
    "name": "Harriet",
    "meaning": "Old Germanic origin, meaning 'home ruler'"
  },
  {
    "name": "Ethel",
    "meaning": "Old English origin, meaning 'noble'"
  },
  {
    "name": "Beatrice",
    "meaning": "Latin origin, meaning 'she who brings happiness'"
  },
  {
    "name": "Florence",
    "meaning": "Latin origin, meaning 'flourishing'"
  },
  {
    "name": "Esther",
    "meaning": "Persian or Hebrew origin, meaning 'star'"
  },
  {
    "name": "Mildred",
    "meaning": "Old English origin, meaning 'gentle strength'"
  },
  {
    "name": "Muriel",
    "meaning": "Irish and Gaelic origin, meaning 'sea bright'"
  },
  {
    "name": "Bessie",
    "meaning": "Hebrew origin, short for Elizabeth"
  },
  {
    "name": "Blanche",
    "meaning": "French and English origin, meaning 'white'"
  },
  {
    "name": "Constance",
    "meaning": "Latin origin, meaning 'steadfast'"
  },
  {
    "name": "Cordelia",
    "meaning": "Celtic origin, meaning 'daughter of the sea'"
  },
  {
    "name": "Cora",
    "meaning": "Greek origin, meaning 'maiden'"
  },
  {
    "name": "Dorinda",
    "meaning": "Greek and Spanish origin, meaning 'gift'"
  },
  {
    "name": "Edna",
    "meaning": "Hebrew origin, meaning 'pleasure'"
  },
  {
    "name": "Effie",
    "meaning": "Greek origin, short for Euphemia, meaning 'well-spoken'"
  },
  {
    "name": "Eleanor",
    "meaning": "Old French and Greek origin, meaning 'bright one'"
  },
  {
    "name": "Elspeth",
    "meaning": "Scottish form of Elizabeth"
  },
  {
    "name": "Emmeline",
    "meaning": "Old Germanic origin, meaning 'work'"
  },
  {
    "name": "Ernestine",
    "meaning": "German form of Ernestina, meaning 'earnest'"
  },
  {
    "name": "Eulalia",
    "meaning": "Greek origin, meaning 'sweet-speaking'"
  },
  {
    "name": "Eulalie",
    "meaning": "French form of Eulalia"
  },
  {
    "name": "Evangeline",
    "meaning": "Greek origin, meaning 'bearer of good news'"
  },
  {
    "name": "Georgiana",
    "meaning": "Greek origin, meaning 'farmer'"
  },
  {
    "name": "Gretchen",
    "meaning": "German form of Margaret, meaning 'pearl'"
  },
  {
    "name": "Guinevere",
    "meaning": "Welsh origin, meaning 'white shadow'"
  },
  {
    "name": "Hattie",
    "meaning": "Old English origin, short for Harriet"
  },
  {
    "name": "Henrietta",
    "meaning": "Old Germanic origin, meaning 'home ruler'"
  },
  {
    "name": "Hortense",
    "meaning": "Latin origin, meaning 'garden'"
  },
  {
    "name": "Ida",
    "meaning": "Old Germanic origin, meaning 'work'"
  },
  {
    "name": "Imogene",
    "meaning": "Celtic origin, meaning 'maiden'"
  },
  {
    "name": "Inez",
    "meaning": "Spanish form of Agnes, meaning 'pure'"
  },
  {
    "name": "Irene",
    "meaning": "Greek origin, meaning 'peace'"
  },
  {
    "name": "Isadora",
    "meaning": "Greek origin, meaning 'gift of Isis'"
  },
  {
    "name": "Kitty",
    "meaning": "Greek origin, short for Katherine, meaning 'pure'"
  },
  {
    "name": "Lavinia",
    "meaning": "Latin origin, meaning 'purity'"
  },
  {
    "name": "Leona",
    "meaning": "Latin origin, meaning 'lioness'"
  },
  {
    "name": "Leonora",
    "meaning": "Greek origin, meaning 'bright'"
  },
  {
    "name": "Letitia",
    "meaning": "Latin origin, meaning 'joy' or 'happiness'"
  },
  {
    "name": "Lillias",
    "meaning": "Scottish form of Lily"
  },
  {
    "name": "Lottie",
    "meaning": "Old French origin, short for Charlotte, meaning 'free woman'"
  },
  {
    "name": "Louisa",
    "meaning": "Germanic origin, meaning 'renowned warrior'"
  },
  {
    "name": "Louise",
    "meaning": "Old Germanic origin, meaning 'renowned warrior'"
  },
  {
    "name": "Lucinda",
    "meaning": "Latin origin, meaning 'light'"
  },
  {
    "name": "Madelief",
    "meaning": "Dutch origin, meaning 'daisy'"
  },
  {
    "name": "Mae",
    "meaning": "English origin, short for Mary or Margaret"
  },
  {
    "name": "Maeve",
    "meaning": "Irish origin, meaning 'intoxicating'"
  },
  {
    "name": "Maida",
    "meaning": "Old English origin, meaning 'maiden'"
  },
  {
    "name": "Mamie",
    "meaning": "English diminutive of Mary"
  },
  {
    "name": "Marcella",
    "meaning": "Latin origin, feminine form of Marcellus"
  },
  {
    "name": "Margot",
    "meaning": "French form of Margaret, meaning 'pearl'"
  },
  {
    "name": "Marjorie",
    "meaning": "Old French and Greek origin, meaning 'pearl'"
  },
  {
    "name": "Mathilda",
    "meaning": "Old Germanic origin, meaning 'might in battle'"
  },
  {
    "name": "Matilda",
    "meaning": "Old Germanic origin, meaning 'battle-mighty'"
  },
  {
    "name": "Maud",
    "meaning": "Old Germanic origin, meaning 'might in battle'"
  },
  {
    "name": "Maude",
    "meaning": "Old Germanic origin, meaning 'mighty battle'"
  },
  {
    "name": "Maxine",
    "meaning": "Latin origin, meaning 'greatest'"
  },
  {
    "name": "Mazie",
    "meaning": "Scottish origin, diminutive of Margaret"
  },
  {
    "name": "Millicent",
    "meaning": "Old Germanic origin, meaning 'work strength'"
  },
  {
    "name": "Minnie",
    "meaning": "Old Germanic origin, short for Wilhelmina"
  },
  {
    "name": "Myrtle",
    "meaning": "Greek origin, from the myrtle plant"
  },
  {
    "name": "Nell",
    "meaning": "Greek origin, short for Eleanor or Helen"
  },
  {
    "name": "Nellie",
    "meaning": "Greek origin, short for Eleanor or Helen"
  },
  {
    "name": "Nettie",
    "meaning": "English diminutive of Antoinette"
  },
  {
    "name": "Odette",
    "meaning": "French origin, meaning 'wealth' or 'fortune'"
  },
  {
    "name": "Opal",
    "meaning": "Sanskrit origin, from the gemstone"
  },
  {
    "name": "Opaline",
    "meaning": "Sanskrit origin, meaning 'precious stone'"
  },
  {
    "name": "Pansy",
    "meaning": "French origin, from the pansy flower"
  },
  {
    "name": "Patience",
    "meaning": "Latin origin, meaning 'patient'"
  },
  {
    "name": "Pauline",
    "meaning": "French form of Paulina, meaning 'small'"
  },
  {
    "name": "Pearl",
    "meaning": "Latin origin, from the gemstone"
  },
  {
    "name": "Peg",
    "meaning": "Greek origin, short for Margaret, meaning 'pearl'"
  },
  {
    "name": "Peggy",
    "meaning": "Greek origin, short for Margaret, meaning 'pearl'"
  },
  {
    "name": "Philomena",
    "meaning": "Greek origin, meaning 'lover of strength'"
  },
  {
    "name": "Phoebe",
    "meaning": "Greek origin, meaning 'bright' or 'radiant'"
  },
  {
    "name": "Prue",
    "meaning": "Latin origin, short for Prudence, meaning 'cautious'"
  },
  {
    "name": "Prudence",
    "meaning": "Latin origin, meaning 'caution' or 'discretion'"
  },
  {
    "name": "Queenie",
    "meaning": "Old English origin, meaning 'queen'"
  },
  {
    "name": "Rae",
    "meaning": "Hebrew origin, short for Rachel, meaning 'ewe'"
  },
  {
    "name": "Rosaline",
    "meaning": "Latin origin, meaning 'tender rose'"
  },
  {
    "name": "Rosamond",
    "meaning": "Old Germanic origin, meaning 'horse protection'"
  },
  {
    "name": "Rosemary",
    "meaning": "Latin origin, from the rosemary herb"
  },
  {
    "name": "Sadie",
    "meaning": "Hebrew origin, form of Sarah, meaning 'princess'"
  },
  {
    "name": "Selma",
    "meaning": "Old Norse and Arabic origin, meaning 'divine protection'"
  },
  {
    "name": "Sibyl",
    "meaning": "Greek origin, meaning 'prophetess'"
  },
  {
    "name": "Susie",
    "meaning": "Hebrew origin, short for Susanna, meaning 'lily'"
  },
  {
    "name": "Sylvia",
    "meaning": "Latin origin, meaning 'forest'"
  },
  {
    "name": "Tess",
    "meaning": "Greek origin, short for Theresa, meaning 'harvest'"
  },
  {
    "name": "Tilda",
    "meaning": "Old Germanic origin, short for Matilda"
  },
  {
    "name": "Tillie",
    "meaning": "Old Germanic origin, short for Matilda"
  },
  {
    "name": "Trudy",
    "meaning": "German origin, short for Gertrude"
  },
  {
    "name": "Vera",
    "meaning": "Russian origin, meaning 'faith'"
  },
  {
    "name": "Viola",
    "meaning": "Latin origin, from the violet flower"
  },
  {
    "name": "Willa",
    "meaning": "Old Germanic origin, meaning 'resolute protection'"
  },
  {
    "name": "Winifred",
    "meaning": "Welsh origin, meaning 'white wave'"
  },
  {
    "name": "Winnie",
    "meaning": "Welsh origin, short for Winifred"
  },
  {
    "name": "Ayla",
    "meaning": "Turkish and Hebrew origin, meaning 'moonlight' or 'oak tree'"
  },
  {
    "name": "Zaylee",
    "meaning": "Modern invented name, possibly meaning 'light'"
  },
  {
    "name": "Brylee",
    "meaning": "Modern invented name, combination of Bry and Lee"
  },
  {
    "name": "Kinley",
    "meaning": "Scottish origin, meaning 'fair warrior'"
  },
  {
    "name": "Rylan",
    "meaning": "Irish origin, variant of Ryan, meaning 'little king'"
  },
  {
    "name": "Braelyn",
    "meaning": "Modern invented name, combining Brae and Lyn"
  },
  {
    "name": "Kaydence",
    "meaning": "Modern variant of Cadence, meaning 'rhythm'"
  },
  {
    "name": "Kyliegh",
    "meaning": "Modern variant of Kylie"
  },
  {
    "name": "Maelyn",
    "meaning": "Modern invented name, combining Mae and Lyn"
  },
  {
    "name": "Raelyn",
    "meaning": "Modern invented name, combining Rae and Lyn"
  },
  {
    "name": "Raelynn",
    "meaning": "Modern invented name, meaning 'ewe meadow'"
  },
  {
    "name": "Rylie",
    "meaning": "Irish origin, variant of Riley"
  },
  {
    "name": "Shyanne",
    "meaning": "Modern variant of Cheyenne"
  },
  {
    "name": "Cheyenne",
    "meaning": "Sioux origin, meaning 'strange speech'"
  },
  {
    "name": "Kadence",
    "meaning": "Latin origin, meaning 'rhythm' or 'flow'"
  },
  {
    "name": "Lakelyn",
    "meaning": "Modern invented name, combining Lake and Lyn"
  },
  {
    "name": "Laylani",
    "meaning": "Hawaiian and Arabic origin, meaning 'heavenly flowers'"
  },
  {
    "name": "Laylin",
    "meaning": "Modern invented name, variant of Layla"
  },
  {
    "name": "Lennox",
    "meaning": "Scottish origin, meaning 'from Levenach'"
  },
  {
    "name": "Lexie",
    "meaning": "Greek origin, short for Alexandra"
  },
  {
    "name": "Liana",
    "meaning": "Latin and French origin, meaning 'to bind'"
  },
  {
    "name": "Lilah",
    "meaning": "Arabic and Hebrew origin, meaning 'night'"
  },
  {
    "name": "Lilyann",
    "meaning": "Modern combined name of Lily and Ann"
  },
  {
    "name": "Livie",
    "meaning": "Latin origin, short for Olivia"
  },
  {
    "name": "Livy",
    "meaning": "Latin origin, short for Olivia, meaning 'olive tree'"
  },
  {
    "name": "Lola",
    "meaning": "Spanish origin, short for Dolores"
  },
  {
    "name": "Lori",
    "meaning": "Latin origin, short for Lorraine or Laura"
  },
  {
    "name": "Lovia",
    "meaning": "Modern invented name"
  },
  {
    "name": "Lumi",
    "meaning": "Finnish origin, meaning 'snow'"
  },
  {
    "name": "Lux",
    "meaning": "Latin origin, meaning 'light'"
  },
  {
    "name": "Lyanna",
    "meaning": "Modern invented name, possibly a combination"
  },
  {
    "name": "Lyra",
    "meaning": "Greek origin, from the lyre instrument"
  },
  {
    "name": "Maci",
    "meaning": "Old French origin, variant of Macy, meaning 'weapon'"
  },
  {
    "name": "Macy",
    "meaning": "Old French origin, meaning 'weapon'"
  },
  {
    "name": "Madicyn",
    "meaning": "Modern variant of Madison"
  },
  {
    "name": "Madisyn",
    "meaning": "Modern variant of Madison, meaning 'son of Maud'"
  },
  {
    "name": "Mae",
    "meaning": "English origin, short for Mary, meaning 'beloved'"
  },
  {
    "name": "Maelys",
    "meaning": "Breton origin, meaning 'prince'"
  },
  {
    "name": "Maeve",
    "meaning": "Irish origin, meaning 'she who intoxicates'"
  },
  {
    "name": "Makayla",
    "meaning": "Hebrew origin, variant of Michaela"
  },
  {
    "name": "Makenna",
    "meaning": "Modern variant of McKenna"
  },
  {
    "name": "Maliah",
    "meaning": "Arabic origin, variant of Maliya"
  },
  {
    "name": "Maliyah",
    "meaning": "Arabic origin, meaning 'queen'"
  },
  {
    "name": "Maris",
    "meaning": "Latin origin, meaning 'of the sea'"
  },
  {
    "name": "Marisol",
    "meaning": "Spanish origin, combining Maria and Sol"
  },
  {
    "name": "Marlee",
    "meaning": "Old English origin, meaning 'pleasant meadow'"
  },
  {
    "name": "Marley",
    "meaning": "Old English origin, meaning 'pleasant meadow'"
  },
  {
    "name": "Marlow",
    "meaning": "Old English origin, meaning 'driftwood'"
  },
  {
    "name": "Marlowe",
    "meaning": "Old English origin, meaning 'driftwood'"
  },
  {
    "name": "Mattea",
    "meaning": "Hebrew origin, feminine form of Matthew"
  },
  {
    "name": "Mavi",
    "meaning": "Turkish origin, meaning 'blue'"
  },
  {
    "name": "Mckenna",
    "meaning": "Irish origin, meaning 'son of Cionaodh'"
  },
  {
    "name": "Meadow",
    "meaning": "English nature name for an open field"
  },
  {
    "name": "Meilani",
    "meaning": "Hawaiian origin, meaning 'heavenly beauty'"
  },
  {
    "name": "Meiloni",
    "meaning": "Modern variant of Melanie"
  },
  {
    "name": "Melani",
    "meaning": "Greek origin, variant of Melanie, meaning 'dark'"
  },
  {
    "name": "Melinda",
    "meaning": "Greek origin, meaning 'gentle'"
  },
  {
    "name": "Melody",
    "meaning": "Greek origin, meaning 'music' or 'song'"
  },
  {
    "name": "Milani",
    "meaning": "Hawaiian origin, meaning 'gentle touch of a breeze'"
  },
  {
    "name": "Milan",
    "meaning": "Slavic origin, meaning 'gracious'"
  },
  {
    "name": "Millie",
    "meaning": "Old Germanic origin, short for Millicent"
  },
  {
    "name": "Mina",
    "meaning": "German and Persian origin, meaning 'love' or 'blue'"
  },
  {
    "name": "Miracle",
    "meaning": "Latin origin, meaning 'wonder'"
  },
  {
    "name": "Mirah",
    "meaning": "Hebrew and Latin origin, meaning 'to wonder'"
  },
  {
    "name": "Mireille",
    "meaning": "Proven\u00e7al origin, meaning 'to admire'"
  },
  {
    "name": "Mireya",
    "meaning": "Spanish form of Mireille"
  },
  {
    "name": "Miriam",
    "meaning": "Hebrew origin, variant of Mary"
  },
  {
    "name": "Mikayla",
    "meaning": "Hebrew origin, variant of Michaela"
  },
  {
    "name": "Mileena",
    "meaning": "Modern invented name"
  }
]